MANIFEST.in
README.md
requirements.txt
setup.py
receipt2vec/__init__.py
receipt2vec/__main__.py
receipt2vec/model.py
receipt2vec/utils.py
receipt2vec.egg-info/PKG-INFO
receipt2vec.egg-info/SOURCES.txt
receipt2vec.egg-info/dependency_links.txt
receipt2vec.egg-info/entry_points.txt
receipt2vec.egg-info/not-zip-safe
receipt2vec.egg-info/requires.txt
receipt2vec.egg-info/top_level.txt
receipt2vec/data/bpe.model
receipt2vec/models/BaseEncoder.py
receipt2vec/models/BiTransformerCnnEncoder.py
receipt2vec/models/__init__.py
receipt2vec/models/models_data/BiTransformerCnnEncodermodels.tar