Metadata-Version: 2.1
Name: receipt2vec
Version: 0.1
Summary: Tool for feature extracting from receipts from Russian stores
Home-page: https://github.com/TinkoffCreditSystems/receipt2vec
Author: Alexey Pichugin
Author-email: a.o.pichugin@tinkoff.ru
License: Apache License 2.0
Platform: UNKNOWN
Classifier: Development Status :: 3 - Alpha
Classifier: Intended Audience :: Science/Research
Classifier: Topic :: Scientific/Engineering :: Artificial Intelligence
Classifier: License :: OSI Approved :: Apache Software License
Classifier: Programming Language :: Python :: 3.6
Classifier: Programming Language :: Python :: 3.7
Classifier: Programming Language :: Python :: 3.8
Classifier: Natural Language :: Russian
